single_instance/__init__.py
single_instance-0.1.2.dist-info/WHEEL
single_instance-0.1.2.dist-info/METADATA
single_instance-0.1.2.dist-info/RECORD
