Metadata-Version: 2.1
Name: single-instance
Version: 0.1.2
Summary: 
Author: fx_kirin
Author-email: fx.kirin@gmail.com
Requires-Python: >=3.6,<4.0
Classifier: Programming Language :: Python :: 3
Classifier: Programming Language :: Python :: 3.6
Classifier: Programming Language :: Python :: 3.7
Classifier: Programming Language :: Python :: 3.8
Requires-Dist: kanilog (>=0.3.2,<0.4.0)
Requires-Dist: logzero (>=1.5.0,<2.0.0)
